bobleesj/__init__.py
bobleesj/release/__init__.py
bobleesj/release/version.py
bobleesj.release-0.1.2.dist-info/AUTHORS.rst
bobleesj.release-0.1.2.dist-info/LICENSE.rst
bobleesj.release-0.1.2.dist-info/METADATA
bobleesj.release-0.1.2.dist-info/WHEEL
bobleesj.release-0.1.2.dist-info/top_level.txt
bobleesj.release-0.1.2.dist-info/RECORD
